txt2ics/__init__.py
txt2ics/__main__.py
txt2ics-0.0.4.dist-info/LICENSE
txt2ics-0.0.4.dist-info/METADATA
txt2ics-0.0.4.dist-info/WHEEL
txt2ics-0.0.4.dist-info/top_level.txt
txt2ics-0.0.4.dist-info/RECORD
