Metadata-Version: 2.1
Name: txt2ics
Version: 0.0.4
Summary: A super-tiny utility that converts your todo.txt file into an iCalendar file.
Author-email: George Politis <gp@superpointer.com>
Project-URL: Homepage, https://github.com/gpolitis/txt2ics
Project-URL: Bug Tracker, https://github.com/gpolitis/txt2ics/issues
Classifier: Programming Language :: Python :: 3
Classifier: License :: OSI Approved :: MIT License
Classifier: Operating System :: OS Independent
Requires-Python: >=3.7
License-File: LICENSE
Requires-Dist: icalendar
Requires-Dist: python-dotenv
